RESTLibrary/JSONSchemaValidator.py
RESTLibrary/JsonCompareEx.py
RESTLibrary/__init__.py
RESTLibrary/data_manager.py
RESTLibrary/input_generator.py
RESTLibrary/json_merge.py
RESTLibrary/jsonpath.py
RESTLibrary/libcommons.py
RESTLibrary/request_info.py
RESTLibrary/request_processor.py
RESTLibrary/rest_keywords.py
RESTLibrary/session_manager.py
RESTLibrary/verification_manager.py
RESTLibrary/version.py
robotframework_restlibrary-1.0.dist-info/LICENSE
robotframework_restlibrary-1.0.dist-info/METADATA
robotframework_restlibrary-1.0.dist-info/WHEEL
robotframework_restlibrary-1.0.dist-info/top_level.txt
robotframework_restlibrary-1.0.dist-info/RECORD
