Metadata-Version: 2.1
Name: robotframework-restlibrary
Version: 1.0
Summary: A REST API Automation Library for Robot Framework
Home-page: https://gitlab.sas.com/sindec/rf-rest
Author: Deepak Chourasia
Author-email: deepak.chourasia@gmail.com
License: UNKNOWN
Project-URL: Bug Tracker, https://gitlab.sas.com/sindec/rf-rest
Platform: UNKNOWN
Classifier: Programming Language :: Python :: 3
Classifier: License :: OSI Approved :: Apache Software License
Classifier: Intended Audience :: Developers
Classifier: Natural Language :: English
Classifier: Topic :: Software Development :: Testing
Classifier: Development Status :: 5 - Production/Stable
Classifier: Framework :: Robot Framework
Requires-Python: >=3.6
License-File: LICENSE
